jlab_aiidatree/__init__.py
jlab_aiidatree/_version.py
jlab_aiidatree/aiida_server.py
jlab_aiidatree/postgres.py
jlab_aiidatree/rest.py
jlab_aiidatree/utils.py
jlab_aiidatree/__pycache__/__init__.cpython-37.pyc
jlab_aiidatree/__pycache__/__init__.cpython-39.pyc
jlab_aiidatree/__pycache__/_version.cpython-37.pyc
jlab_aiidatree/__pycache__/_version.cpython-39.pyc
jlab_aiidatree/__pycache__/postgres.cpython-37.pyc
jlab_aiidatree/__pycache__/postgres.cpython-39.pyc
jlab_aiidatree/__pycache__/rest.cpython-37.pyc
jlab_aiidatree/__pycache__/rest.cpython-39.pyc
jlab_aiidatree/labextension/build_log.json
jlab_aiidatree/labextension/package.json
jlab_aiidatree/labextension/schemas/jlab_aiidatree/package.json.orig
jlab_aiidatree/labextension/schemas/jlab_aiidatree/settings-aiidatree.json
jlab_aiidatree/labextension/static/lib_index_js.45036b79273ef0585857.js
jlab_aiidatree/labextension/static/lib_index_js.45036b79273ef0585857.js.map
jlab_aiidatree/labextension/static/lib_index_js.7f170331cb2711f69751.js
jlab_aiidatree/labextension/static/lib_index_js.7f170331cb2711f69751.js.map
jlab_aiidatree/labextension/static/remoteEntry.15dbd4df60aa10e40014.js
jlab_aiidatree/labextension/static/remoteEntry.15dbd4df60aa10e40014.js.map
jlab_aiidatree/labextension/static/remoteEntry.8295470e284cfa8604da.js
jlab_aiidatree/labextension/static/remoteEntry.8295470e284cfa8604da.js.map
jlab_aiidatree/labextension/static/style.js
jlab_aiidatree/labextension/static/style_index_js.3314ac47f5040e934d83.js
jlab_aiidatree/labextension/static/style_index_js.3314ac47f5040e934d83.js.map
jlab_aiidatree/labextension/static/vendors-node_modules_css-loader_dist_runtime_api_js-node_modules_css-loader_dist_runtime_cssW-926fd9.afee0452e243dca76304.js
jlab_aiidatree/labextension/static/vendors-node_modules_css-loader_dist_runtime_api_js-node_modules_css-loader_dist_runtime_cssW-926fd9.afee0452e243dca76304.js.map
jlab_aiidatree-0.2.0.dist-info/LICENSE
jlab_aiidatree-0.2.0.dist-info/METADATA
jlab_aiidatree-0.2.0.dist-info/WHEEL
jlab_aiidatree-0.2.0.dist-info/top_level.txt
jlab_aiidatree-0.2.0.dist-info/RECORD
