Metadata-Version: 2.1
Name: jlab-aiidatree
Version: 0.2.0
Summary: A JupyterLab extension for exploring AiiDA databases.
Home-page: https://github.com/chrisjsewell/jlab_aiidatree
Author: Chris Sewell
Author-email: chrisj_sewell@hotmail.com
License: BSD-3-Clause
Keywords: Jupyter,JupyterLab,JupyterLab3
Platform: Linux
Platform: Mac OS X
Platform: Windows
Classifier: License :: OSI Approved :: BSD License
Classifier: Programming Language :: Python
Classifier: Programming Language :: Python :: 3
Classifier: Programming Language :: Python :: 3.6
Classifier: Programming Language :: Python :: 3.7
Classifier: Programming Language :: Python :: 3.8
Classifier: Programming Language :: Python :: 3.9
Classifier: Framework :: Jupyter
Requires-Python: >=3.6
Requires-Dist: jupyter-server (<2,>=1.6)
Provides-Extra: aiida
Requires-Dist: aiida-core (~=1.6.3) ; extra == 'aiida'
Provides-Extra: dev
Requires-Dist: jupyterlab (~=3.0) ; extra == 'dev'
Requires-Dist: jupyter-packaging ; extra == 'dev'
